pytest_webdriver.py
pytest_webdriver-1.8.0.dist-info/LICENSE
pytest_webdriver-1.8.0.dist-info/METADATA
pytest_webdriver-1.8.0.dist-info/WHEEL
pytest_webdriver-1.8.0.dist-info/entry_points.txt
pytest_webdriver-1.8.0.dist-info/top_level.txt
pytest_webdriver-1.8.0.dist-info/RECORD
